event_transforms_polars/__init__.py
event_transforms_polars/coalesce.py
event_transforms_polars-0.0.1.dist-info/LICENCE
event_transforms_polars-0.0.1.dist-info/METADATA
event_transforms_polars-0.0.1.dist-info/WHEEL
event_transforms_polars-0.0.1.dist-info/top_level.txt
event_transforms_polars-0.0.1.dist-info/RECORD
